ja_sentence/__init__.py
ja_sentence/tokenizer.py
ja_sentence-0.0.5.dist-info/LICENSE.txt
ja_sentence-0.0.5.dist-info/METADATA
ja_sentence-0.0.5.dist-info/WHEEL
ja_sentence-0.0.5.dist-info/top_level.txt
ja_sentence-0.0.5.dist-info/RECORD
